claude_conversation_extractor/__init__.py
claude_conversation_extractor/cli.py
claude_conversation_extractor/extractor.py
claude_conversation_extractor/markdown_converter.py
claude_conversation_extractor/models.py
claude_chat_extractor-0.2.1.dist-info/METADATA
claude_chat_extractor-0.2.1.dist-info/WHEEL
claude_chat_extractor-0.2.1.dist-info/entry_points.txt
claude_chat_extractor-0.2.1.dist-info/licenses/LICENSE
claude_chat_extractor-0.2.1.dist-info/RECORD
