Metadata-Version: 2.4
Name: claude-chat-extractor
Version: 0.2.1
Summary: A command-line tool to extract and convert Claude conversations to markdown format efficiently.
Project-URL: Homepage, https://github.com/jmorenobl/claude-conversation-extractor
Project-URL: Documentation, https://github.com/jmorenobl/claude-conversation-extractor#readme
Project-URL: Repository, https://github.com/jmorenobl/claude-conversation-extractor.git
Project-URL: Issues, https://github.com/jmorenobl/claude-conversation-extractor/issues
Author-email: Jorge MB <jmorenobl@gmail.com>
License: MIT
License-File: LICENSE
Keywords: anthropic,claude,cli,conversation,extractor,markdown
Classifier: Development Status :: 4 - Beta
Classifier: Intended Audience :: Developers
Classifier: License :: OSI Approved :: MIT License
Classifier: Operating System :: OS Independent
Classifier: Programming Language :: Python :: 3
Classifier: Programming Language :: Python :: 3.12
Classifier: Programming Language :: Python :: 3.13
Classifier: Topic :: Software Development :: Libraries :: Python Modules
Classifier: Topic :: Text Processing :: Markup
Classifier: Topic :: Utilities
Requires-Python: >=3.12
Requires-Dist: click>=8.2.1
Requires-Dist: ijson>=3.4.0
Requires-Dist: pydantic>=2.11.7
Requires-Dist: rich>=14.1.0
